discovermidi/AdvancedSyllablesSearch.py
discovermidi/HaystackSearch.py
discovermidi/MIDI.py
discovermidi/NumbaHaystackSearch.py
discovermidi/README.md
discovermidi/SyllablesSearch.py
discovermidi/TCUPY.py
discovermidi/TMELODIES.py
discovermidi/TMIDIX.py
discovermidi/TPLOTS.py
discovermidi/__init__.py
discovermidi/directory_tree.py
discovermidi/fast_parallel_extract.py
discovermidi/genres.py
discovermidi/helpers.py
discovermidi/midi_to_colab_audio.py
discovermidi/plots_and_reports.py
discovermidi/search_and_filter.py
discovermidi/x_transformer_2_3_1.py
discovermidi/artwork/Discover-MIDI-Dataset.png
discovermidi/artwork/Project-Los-Angeles.png
discovermidi/artwork/README.md
discovermidi/artwork/Tegridy-Code-2025.png
discovermidi/artwork/__init__.py
discovermidi/midi_loops_extractor/README.md
discovermidi/midi_loops_extractor/__init__.py
discovermidi/midi_loops_extractor/corr_mat.py
discovermidi/midi_loops_extractor/corr_mat_fast.py
discovermidi/midi_loops_extractor/nomml.py
discovermidi/midi_loops_extractor/note_set.py
discovermidi/midi_loops_extractor/note_set_fast.py
discovermidi/midi_loops_extractor/process_file.py
discovermidi/midi_loops_extractor/process_file_fast.py
discovermidi-25.12.49.dist-info/licenses/LICENSE
discovermidi-25.12.49.dist-info/METADATA
discovermidi-25.12.49.dist-info/WHEEL
discovermidi-25.12.49.dist-info/top_level.txt
discovermidi-25.12.49.dist-info/RECORD
