Metadata-Version: 2.4
Name: discovermidi
Version: 25.12.49
Summary: Ultimate MIDI dataset for MIDI music discovery and symbolic music AI purposes
Author-email: Alex Lev <alexlev61@proton.me>
Maintainer-email: Alex Lev <alexlev61@proton.me>
License-Expression: Apache-2.0
Project-URL: Homepage, https://github.com/asigalov61/discovermidi
Project-URL: SoundCloud, https://soundcloud.com/aleksandr-sigalov-61/
Project-URL: Documentation, https://github.com/asigalov61/discovermidi
Project-URL: Issues, https://github.com/asigalov61/discovermidi/issues
Project-URL: Discussions, https://github.com/asigalov61/discovermidi/discussions
Project-URL: Dataset, https://huggingface.co/datasets/projectlosangeles/Discover-MIDI-Dataset
Keywords: MIDI,MIDI dataset,MIDI processing,symbolic music,symbolic dataset,music,music AI,music dataset,music information retrieval,MIR,music discovery,music search,music similarity,music metadata,music generation,music recommendation,dataset,open dataset,research,deep learning,machine learning,AI,huggingface datasets,musicology,music analysis
Classifier: Development Status :: 5 - Production/Stable
Classifier: Intended Audience :: Developers
Classifier: Intended Audience :: Science/Research
Classifier: Intended Audience :: Education
Classifier: Operating System :: OS Independent
Classifier: Programming Language :: Python :: 3
Classifier: Programming Language :: Python :: 3 :: Only
Classifier: Programming Language :: Python :: 3.8
Classifier: Programming Language :: Python :: 3.9
Classifier: Programming Language :: Python :: 3.10
Classifier: Programming Language :: Python :: 3.11
Classifier: Programming Language :: Python :: 3.12
Classifier: Topic :: Multimedia :: Sound/Audio
Classifier: Topic :: Multimedia :: Sound/Audio :: MIDI
Classifier: Topic :: Scientific/Engineering :: Artificial Intelligence
Classifier: Topic :: Scientific/Engineering :: Information Analysis
Classifier: Topic :: Software Development :: Libraries :: Python Modules
Classifier: Environment :: Console
Classifier: Natural Language :: English
Classifier: Typing :: Typed
Requires-Python: >=3.8
License-File: LICENSE
Requires-Dist: tqdm
Requires-Dist: ipywidgets
Requires-Dist: scikit-learn
Requires-Dist: scipy
Requires-Dist: matplotlib
Requires-Dist: hf-transfer
Requires-Dist: huggingface_hub
Requires-Dist: torch
Requires-Dist: midirenderer
Requires-Dist: mididoctor
Requires-Dist: numpy==1.26.4
Provides-Extra: loops
Requires-Dist: pretty-midi; extra == "loops"
Requires-Dist: symusic; extra == "loops"
Requires-Dist: miditok; extra == "loops"
Requires-Dist: numba; extra == "loops"
Requires-Dist: numpy==1.26.4; extra == "loops"
Provides-Extra: full
Requires-Dist: pretty-midi; extra == "full"
Requires-Dist: symusic; extra == "full"
Requires-Dist: miditok; extra == "full"
Requires-Dist: numba; extra == "full"
Requires-Dist: networkx; extra == "full"
Requires-Dist: cupy-cuda13x; extra == "full"
Requires-Dist: einops; extra == "full"
Requires-Dist: einx; extra == "full"
Requires-Dist: nltk; extra == "full"
Requires-Dist: numpy==1.26.4; extra == "full"
Dynamic: license-file
